{
    "url": "https://panopto.dtu.dk/Panopto/Pages/Viewer.aspx?id=11faaf4a-e5b0-4676-81b3-af2800a07cc9",
    "parentName": "E14/F15",
    "parentURL": "https://panopto.dtu.dk/Panopto/Pages/Sessions/List.aspx#folderID=%224bdf7bf6-5fd9-4c69-86a8-af24007c1de6%22",
    "title": "1. ord. diff-ligninger Del 2",
    "detailsTab": "1. ord. diff-ligninger Del 2\nForelæsning med Ulrik Engelund Pedersen. Kapitler: 02:00 - Panserformel - General Løsning Til Et 1.Ordens Lineær Diff.Lign.; 10:00 - Ex: Panserformel; 16:00 - Ex: Homogen Diff.Lign. Panserformel Fuldstændig Løsning; 19:15 - Entydighedssætning; 23:00 - Ex: Løsningskurven Ved Brug Af Begyndelsespunktet x0; 26:30 - Ex: Gæt Af Partikulær Løsning Til Den Inhomogene Løsning; 34:45 - Maple: 1.Orden Lineære Differentialligninger;\nUploadet af: jectli@llab.dtu.dk\nUploaddato: 12.23 19.10.2018\nAntal visninger: 1\nKalturaId: 0_vnxziewa\nperson_outline\nPanopto Team",
    "video_duration": 2435.2526666
}