{
    "url": "https://panopto.dtu.dk/Panopto/Pages/Viewer.aspx?id=b46b1e61-bf5f-4d4b-9c02-af2800781d09",
    "parentName": "E11/F12",
    "parentURL": "https://panopto.dtu.dk/Panopto/Pages/Sessions/List.aspx#folderID=%22d81e2948-a527-4125-a9e6-af24007bbfa1%22",
    "title": "Brug af matematik i kemi",
    "detailsTab": "Brug af matematik i kemi\nPeptalk. Kapitler: 00:00 - Introduktion; 01:30 - Termodynamik; 02:15 - Bevægelsesligninger; 04:00 - Trasportegenskabet; 06:15 - Hydrogenatomet; 09:15 - Hydrogenmolekylet; 10:30 - Energiniveauer i molekylet; 11:30 Energilandskab for kemisk reaktion; 16:45 - Rational udvikling af superstabile laccaser;\nUploadet af: jectli@llab.dtu.dk\nUploaddato: 12.25 19.10.2018\nAntal visninger: 2\nKalturaId: 0_j8h8po8w\nperson_outline\nPanopto Team",
    "video_duration": 1077.59
}