{
    "url": "https://panopto.dtu.dk/Panopto/Pages/Viewer.aspx?id=78bc64d2-e344-4104-b1a6-af2800b37c96",
    "parentName": "E14/F15",
    "parentURL": "https://panopto.dtu.dk/Panopto/Pages/Sessions/List.aspx#folderID=%224bdf7bf6-5fd9-4c69-86a8-af24007c1de6%22",
    "title": "Flader/Fladeintegraler Del 1",
    "detailsTab": "Flader/Fladeintegraler Del 1\nForelæsning med Ulrik Engelund Pedersen. Kapitler: 00:00 - Dagsorden: Fladeintegraler, Parametrisering & Areal Af Flader; 02:45 - Plan Integral; 05:30 - Fladeintegral; 11:15 - Akse-Parallel Parametrisering Af Områder I Rummet; 14:30 - Ex: Parametrisering Af Paraboloide; 18:45 - Cylinderflade Parametrisering; 22:45 - Afskåret Cylinderflade Parametrisering; 28:00 - Kugleflade Parametrisering: Profilkurve; 37:00 - Omdrejning Af Profilkurven Ved Multiplikation Med Positiv Ortogonal Matrix Q; 43:15 - Maple: Parametrisering Af Flader; 45:45 - Maple Eks 2 Fejl - Parameterområdet Skal Være u [1,4];\nUploadet af: jectli@llab.dtu.dk\nUploaddato: 12.23 19.10.2018\nAntal visninger: 1\nKalturaId: 0_009sm30p\nperson_outline\nPanopto Team",
    "video_duration": 3029.386
}