{
    "url": "https://panopto.dtu.dk/Panopto/Pages/Viewer.aspx?id=8728365c-ac65-40e5-a690-af08007e0f73",
    "parentName": "E11/F12",
    "parentURL": "https://panopto.dtu.dk/Panopto/Pages/Sessions/List.aspx#folderID=%22d81e2948-a527-4125-a9e6-af24007bbfa1%22",
    "title": "Taylors Formler Del1",
    "detailsTab": "Taylors Formler Del1\nTaylors Formler; Kapitler: 00:00 - Introduction; 03:15 - Eksempel; 12:00 - Ad 1; 21:45 - Approksimerende polynomial af n'te grad; 26:15 - Maple;\nUploadet af: jectli@llab.dtu.dk\nUploaddato: 12.38 19.10.2018\nAntal visninger: 3\nKalturaId: 0_6lornwoq\nperson_outline\nPanopto Team",
    "video_duration": 2261.45
}