{
    "url": "https://panopto.dtu.dk/Panopto/Pages/Viewer.aspx?id=a1d4ece5-5b77-47bc-b171-af2701290292",
    "parentName": "E13/F14",
    "parentURL": "https://panopto.dtu.dk/Panopto/Pages/Sessions/List.aspx#folderID=%22a488e829-1543-4366-ba0f-af24007c188c%22",
    "title": "Funktionsrum Del 2",
    "detailsTab": "Funktionsrum Del 2\nForelæsning med Michael Pedersen. Kapitler: 00:00 - Ex1: Basis For Hyperbolske Funktioner; 03:15 - Lineært Uafhængighed Af cosh Og sinh; 05:00 - Afbildningsmatrix For Basis a; 11:15 - Afbildningsmatricen Basisskift; 12:30 - Differentiation Af Hyperbolske Funktioner; 15:15 - Basisskift; 20:00 - Invers Basiskiftematrix; 34:30 - Diagonal Matrice Ved Basiskift; 35:00 - Vil Vores Helte Klare Tema Øvelse? Find Ud I Den Næste Afsnit Af Mat C;\nUploadet af: jectli@llab.dtu.dk\nUploaddato: 12.40 19.10.2018\nAntal visninger: 1\nKalturaId: 0_u73c37dy\nperson_outline\nPanopto Team",
    "video_duration": 2209.3326666
}