{
    "url": "https://panopto.dtu.dk/Panopto/Pages/Viewer.aspx?id=5d2ec4f9-b442-42ce-a839-af27016b2f7f",
    "parentName": "E16/F17",
    "parentURL": "https://panopto.dtu.dk/Panopto/Pages/Sessions/List.aspx#folderID=%22b2eba804-35e8-40cf-9677-af24007c2766%22",
    "title": "Eksamens gennemgang del 1",
    "detailsTab": "Eksamens gennemgang del 1\nGennemgang af eksamenssættet fra december 2015\nUploadet af: jectli@llab.dtu.dk\nUploaddato: 12.36 19.10.2018\nAntal visninger: 7\nKalturaId: 0_mq33b6hd\nperson_outline\nPanopto Team",
    "video_duration": 3164.7033333
}