{
    "url": "https://panopto.dtu.dk/Panopto/Pages/Viewer.aspx?id=dccf2041-b097-4c3c-a273-af080087740e",
    "parentName": "E12/F13",
    "parentURL": "https://panopto.dtu.dk/Panopto/Pages/Sessions/List.aspx#folderID=%226da089b0-b31d-4014-90fa-af24007c04fd%22",
    "title": "Stokes Potentialer Del1",
    "detailsTab": "Stokes Potentialer Del1\nForelæsning med Poul Hjorth. Kapitler: 00:45 - Dagsorden: Stokes Sætning; 01:45 - Gauss' Sætning Repetition; 04:45 - Fluxintegralet Over Randen; 06:30 - Stokes' Sætning Introduktion; 06:45 - Åben Flade, Randkurve; 15:30 - Stokes' Sætning For Et Givet Vektorfelt; 19:45 - Ex1: Eksamen Maj 2012; 28:00 - Find Div(V) Og Rot(V); 31:30 - Bestem Den Tangentielle Integral For Vektorfeltet;\nUploadet af: jectli@llab.dtu.dk\nUploaddato: 12.38 19.10.2018\nAntal visninger: 3\nKalturaId: 0_6d6xmbei\nperson_outline\nPanopto Team",
    "video_duration": 2480.138
}