{
    "url": "https://panopto.dtu.dk/Panopto/Pages/Viewer.aspx?id=ff4cf23c-eb0f-4cd7-991f-af0f000904cf",
    "parentName": "E21/F22",
    "parentURL": "https://panopto.dtu.dk/Panopto/Pages/Sessions/List.aspx#folderID=%22c7565316-b5fa-4468-935d-af24007c4080%22",
    "title": "Uge 2, Lille Dag: Keglesnit",
    "detailsTab": "Uge 2, Lille Dag: Keglesnit\nEn andengradsligning i to variable repræsenterer et keglesnit hvis hovedformer er ellipser, hyperbler og parabler. Så dagens opgave er i kort form denne: Hvis du har en andengradligning i to variable, hvordan kan du så afgøre hvilken type det er, og hvordan ligger det pågældende keglesnit i koordinatsystemet? Det kræver beherskelse af teknikkerne kvadratkomplettering og reduktion af kvadratisk form, så dem indfører vi og træner i dag.\nUploadet af: Medialab@dtu.dk\nUploaddato: 11.55 11.02.2022\nAntal visninger: 138\nKalturaId: 0_xxooi0h1\nperson_outline\nPanopto Team",
    "video_duration": 3229.506155499989
}