{
    "url": "https://panopto.dtu.dk/Panopto/Pages/Viewer.aspx?id=91e90026-e2da-482f-9d60-af2701568976",
    "parentName": "E16/F17",
    "parentURL": "https://panopto.dtu.dk/Panopto/Pages/Sessions/List.aspx#folderID=%22b2eba804-35e8-40cf-9677-af24007c2766%22",
    "title": "Lineære ligningssystemer og matrixregning Del 2",
    "detailsTab": "Lineære ligningssystemer og matrixregning Del 2\nMatrixalgebra: Addition, Multiplikation, Transponering, Matrix-Vektor produkt. Eksempel: Gauss-elimination, Rang, Ledende 1-taller & Antallet af frie variable.\nUploadet af: jectli@llab.dtu.dk\nUploaddato: 12.37 19.10.2018\nAntal visninger: 1\nKalturaId: 0_5avolj7x\nperson_outline\nPanopto Team",
    "video_duration": 2587.5726666
}