{
    "url": "https://panopto.dtu.dk/Panopto/Pages/Viewer.aspx?id=0d63e7ad-531b-44e1-868d-af0c01866afe",
    "parentName": "E21/F22",
    "parentURL": "https://panopto.dtu.dk/Panopto/Pages/Sessions/List.aspx#folderID=%22c7565316-b5fa-4468-935d-af24007c4080%22",
    "title": "Uge 13, Store Dag: Stokes’ sætning og potentialer",
    "detailsTab": "Uge 13, Store Dag: Stokes’ sætning og potentialer\nI dag skal vi arbejde med en sætning, som på mange måder kan sammenlignes med - og er lige så fantastisk som - Gauss’s sætning. Det handler om det tangentielle kurveintegral af et vektorfelt langs en lukket kurve, også kaldet cirkulationen af vektorfeltet langs den lukkede kurve. Stokes’ rotationssætning giver en forbindelse mellem denne cirkulation og fluxen af vektorfeltets rotation gennem en vilkårlig flade, der har den lukkede kurve som randkurve.\n\nEn almindelig kontinuert, reel funktion af en variabel har en stamfunktion, dvs. en funktion som differentieret giver funktionen selv. I forbindelse med tangentielt kurveintegral, så vi at nogle vektorfelter kunne udtrykkes som gradienten af en funktion, et såkaldt skalarpotential. Problemet idag er givet et vektorfelt, vil vi forsøge at finde de stamvektorfelter (vektorpotentialer), hvorom der gælder at hvis vi tager rotationen af stamvektorfeltet giver det vektorfeltet selv.\n\nDagens nøglebegreber\nCirkulationen af et vektorfelt langs en lukket kurve. Fluxen af et vektorfelts rotation gennem en åben flade. Højrekonventionen og højreskrue. Et vektorfelts vridning af en flade. Stamvektorfelt (eller vektorpotential) til et divergensfrit vektorfelt.\n\n\nUploadet af: ksch@dtu.dk\nUploaddato: 09.58 28.03.2022\nAntal visninger: 505\nKalturaId: 0_q9u4wmfl\nperson_outline\nPanopto Team",
    "video_duration": 7007.987666599994
}