{
    "url": "https://panopto.dtu.dk/Panopto/Pages/Viewer.aspx?id=5483c385-ce3f-4d82-8c29-af0800941a95",
    "parentName": "E11/F12",
    "parentURL": "https://panopto.dtu.dk/Panopto/Pages/Sessions/List.aspx#folderID=%22d81e2948-a527-4125-a9e6-af24007bbfa1%22",
    "title": "Tangetiel Kurveintegral Del 1",
    "detailsTab": "Tangetiel Kurveintegral Del 1\nVektorfelter. Kapitler: 00:00 - Intro; 01:45 - Eksempel På én krafts arbejde; 17:00 - Parameter i Rummet; 27:45 - Eksempel; 40:00 - Eksempel;\nUploadet af: jectli@llab.dtu.dk\nUploaddato: 12.38 19.10.2018\nAntal visninger: 1\nKalturaId: 0_uqdrrxvh\nperson_outline\nPanopto Team",
    "video_duration": 2735.81
}