{
    "url": "https://panopto.dtu.dk/Panopto/Pages/Viewer.aspx?id=2f166726-d455-494c-80c2-af1400d1cbbd",
    "parentName": "E21/F22",
    "parentURL": "https://panopto.dtu.dk/Panopto/Pages/Sessions/List.aspx#folderID=%22c7565316-b5fa-4468-935d-af24007c4080%22",
    "title": "Uge 3, Lille Dag: Differentiabilitet",
    "detailsTab": "Uge 3, Lille Dag: Differentiabilitet\nI gymnasiet har du sikkert set differentialkvotient indført som grænseværdien af en differenskvotient:\n\nf′(xo)=f(x)−f(xo)x−xoforx→xo.\nf\n′\n(\nx\no\n)\n=\nf\n(\nx\n)\n−\nf\n(\nx\no\n)\nx\n−\nx\no\nf\no\nr\nx\n→\nx\no\n.\nI dag indfører vi alternativt differentialkvotient ved hjælp af epsilonfunktioner, det får vi nemlig brug for når vi senere skal generalisere differentiabilitet til funktioner af flere variable. Som en forsmag skal vi differentiere komplekse funktioner af en reel variabel. Herigennem bliver vi i stand til at differentiere en vigtig variant af den komplekse eksponentialfunktion. Bag ved det hele ligger de sædvanlige regneregler for differentialkvotient. Det er helt afgørende at du får tjek på dem, og hvordan differentiation i det hele taget udføres!\n\nDagens nøglebegreber\nEpsilonfunktioner. Differentiation og differentiationssregler for reelle funktioner. Omvendte funktioner og deres afledede funktioner. Tangens og acustangens. Komplekse funktioner af en reel variabel og deres afledede funktioner. Differentiationer af den komplekse eksponentialfunktion.\nUploadet af: ksch@dtu.dk\nUploaddato: 07.55 16.09.2021\nAntal visninger: 284\nKalturaId: 0_j0z4bajt\nperson_outline\nPanopto Team",
    "video_duration": 3866.0336665999985
}