{
    "url": "https://panopto.dtu.dk/Panopto/Pages/Viewer.aspx?id=b12b5d8f-5b07-4a5d-9176-af25013ad3d0",
    "parentName": "E19/F20",
    "parentURL": "https://panopto.dtu.dk/Panopto/Pages/Sessions/List.aspx#folderID=%22b4225918-94ee-4ed5-963a-af24007c3628%22",
    "title": "Uge 1, Store Dag: Funktioner af to variable, del 2",
    "detailsTab": "Uge 1, Store Dag: Funktioner af to variable, del 2\nVi skal i foråret arbejde med funktioner som er afhængige af to (eller flere) variable. I denne uge undersøger vi hvordan vi kan overføre begreber som kontinuitet og differentiabilitet til den slags funktioner, og hvordan kan vi tegne deres grafer? For at kunne beskrive funktionernes vækst indfører vi begreber som niveaukurver, partielt afledede, gradienter og retningsafledede. Bjerge og bjergvandringer er yndede metaforer inden for emnet, dem undgår du heller ikke her!\nUploadet af: Medialab@dtu.dk\nUploaddato: 12.14 03.02.2020\nAntal visninger: 2095\nKalturaId: 0_6mjtn78v\nperson_outline\nPanopto Team",
    "video_duration": 2609.6766555
}